verilog_processor/alu.v
`define OP 8
`define ADDR 8

module alu (clk, nrst, alu_op, alu_zero, alu_valid, alu_bus);

// Interface Defenitions
input clk;  // Clock input
input nrst; // reset (active low)
output alu_zero;    // ALU is alu_zero
input alu_valid;    // ALU output is alu_valid

inout [`OP+`ADDR-1:0] alu_bus;  // ALU alu_bus
input [`OP-1:0] alu_op;    // ALU OP code

// Register Defenitions
reg alu_zero; // ALU is alu_zero

reg [`OP+`ADDR-1:0] acc; // Accumulator
reg [`OP+`ADDR-1:0] alu_reg;    // Accumulator Reg

assign alu_bus = alu_valid ? alu_reg : 'bz;

always @(posedge clk) begin
    if(nrst==0) begin
        acc <= 0;
    end
    else begin
        case (alu_op)
            8'h00 : acc <= alu_bus;
            8'h01 : acc <= acc + alu_bus;
            8'h02 : acc <= ~alu_bus;
            8'h03 : acc <= acc | alu_bus;
            8'h04 : acc <= acc & alu_bus;
            8'h05 : acc <= acc ^ alu_bus;
            8'h06 : acc <= acc + 1;
            8'h07 : alu_reg <= acc;
            default: acc = 0;
        endcase
        if(acc==0) begin
            alu_zero <= 1;
        end
        else begin
            alu_zero <= 0;
        end
    end
end

endmodule

verilog_processor/alu_tb.v
`define OP 8
`define ADDR 8
`timescale 1ns/100ps

module alu_tb();
// declare the counter signals
reg clk;
reg nrst;
reg alu_valid;
wire alu_zero;

wire [`OP+`ADDR-1:0] alu_bus;
reg [`OP-1:0] opcode;
reg [`OP+`ADDR-1:0] alu_reg;

assign alu_bus = alu_reg;

// Set up the initial varaibles and reset
initial begin
    $dumpfile("alu_tb.vcd");
    $dumpvars();

    $display ("time\t clk reset inc load valid data");
    $monitor ("%g\t %b %b %b %b %b",
    $time, clk, nrst, alu_zero, alu_valid, opcode, alu_bus);
    clk = 1;    // initialize the clock to 1
    nrst = 1;   // set the reset to 1 (not reset)
    alu_valid = 0;
    opcode = 8'h00;
    alu_reg = 'bz;
    #5 nrst = 0;    // reset = 0 : resets the counter
    #10 nrst = 1;   // reset back to 1 : counter can start
    alu_valid = 1;
    #10 alu_valid = 0;  // reset back to 1 : counter can start
    #10 alu_reg = 16'h0012;
    #200 $finish;   // Finish the simulation
end

// Clock generator
always begin
    #5 clk = ~clk;  // clock every 5 time slots
end

//assign data = datareg;

// Connect DUT to test bench
alu DUT (clk, nrst, opcode, alu_zero, alu_valid, alu_bus);

endmodule

verilog_processor/alu_tb.vcd
$date
	Sat Oct  9 06:41:15 2021
$end
$version
	Icarus Verilog
$end
$timescale
	100ps
$end
$scope module alu_tb $end
$var wire 16 ! alu_bus [15:0] $end
$var wire 1 " alu_zero $end
$var reg 16 # alu_reg [15:0] $end
$var reg 1 $ alu_valid $end
$var reg 1 % clk $end
$var reg 1 & nrst $end
$var reg 8 ' opcode [7:0] $end
$scope module DUT $end
$var wire 16 ( alu_bus [15:0] $end
$var wire 8 ) alu_op [7:0] $end
$var wire 1 $ alu_valid $end
$var wire 1 % clk $end
$var wire 1 & nrst $end
$var reg 16 * acc [15:0] $end
$var reg 16 + alu_reg [15:0] $end
$var reg 1 " alu_zero $end
$upscope $end
$upscope $end
$enddefinitions $end
#0
$dumpvars
bx +
bx *
b0 )
bz (
b0 '
1&
1%
0$
bz #
0"
bz !
$end
#50
0%
0&
#100
b0 *
1%
#150
bx !
bx (
0%
1$
1&
#200
1"
bx *
1%
#250
bz !
bz (
0%
0$
#300
0"
bz *
1%
#350
0%
b10010 !
b10010 (
b10010 #
#400
b10010 *
1%
