verilog_processor/mar.v
`define ADDR 8
`define OP 8
 
 module mar (clk, nrst, mar_load, mar_bus, address);

 input clk;
 input nrst;
 input mar_load;

 input [`OP+`ADDR-1:0] mar_bus;
 output [`ADDR-1:0] address;

 wire [`OP+`ADDR-1:0] mar_bus;
 reg [`ADDR-1:0] address;

 always @(posedge clk) begin
    if(nrst==0) begin
        address <= 0;
    end
    else begin
        if(mar_load==1) begin
            address <= mar_bus[`ADDR-1:0];
        end
    end
end

endmodule

verilog_processor/mar_tb.v
`define OP 8
`define ADDR 8

module mar_tb();
// declare the counter signals
reg clk;
reg nrst;
reg mar_load;

reg [`OP+`ADDR-1:0] data;
wire [`ADDR-1:0] address;

// set up the initial variables and reset
initial begin
    $dumpfile("mar_tb.vcd");
    $dumpvars();
    $display("time\t clk reset inc load valid data");
    $monitor("%g\t %b %b %b %b %b",
    $time, clk, nrst, mar_load, data, address);
    clk = 1;    // initialize the clock to 1
    nrst = 1;   // set the reset to 1 (not reset)
    mar_load = 0;
    data = 16'b0000000000001111;
    #5 nrst = 0; // reset = 0 : resets the counter
    #10 nrst = 1;   // reset back to 1 : counter can start
    #10 mar_load = 1;
    #10 mar_load = 0;
    #10 data = 16'bz;
    #200 $finish;   // Finish the simulation
end

// Clock generator
always begin
    #5 clk = ~clk; // Clock every 5 time slots
end

// assign data = datareg

// Connect DUT to test bench
mar DUT (clk, nrst, mar_load, data, address);

endmodule

verilog_processor/mar_tb.vcd
$date
	Thu Oct  7 14:41:09 2021
$end
$version
	Icarus Verilog
$end
$timescale
	1s
$end
$scope module mar_tb $end
$var wire 8 ! address [7:0] $end
$var reg 1 " clk $end
$var reg 16 # data [15:0] $end
$var reg 1 $ mar_load $end
$var reg 1 % nrst $end
$scope module DUT $end
$var wire 1 " clk $end
$var wire 16 & mar_bus [15:0] $end
$var wire 1 $ mar_load $end
$var wire 1 % nrst $end
$var reg 8 ' address [7:0] $end
$upscope $end
$upscope $end
$enddefinitions $end
#0
$dumpvars
bx '
b1111 &
1%
0$
b1111 #
1"
bx !
$end
#5
0"
0%
#10
b0 !
b0 '
1"
#15
0"
1%
#20
1"
#25
0"
1$
#30
b1111 !
b1111 '
1"
#35
0"
0$
#40
1"
#45
0"
bz #
bz &
