verilog_processor/mdr.v
`define OP 8
`define ADDR 8

module mdr (clk, nrst, mdr_load, mdr_valid, mem_bus, mdr_bus);

input clk;
input nrst;
input mdr_valid;
input mdr_load;
//input mem_bus;

inout [`OP+`ADDR-1:0] mdr_bus;
input [`OP+`ADDR-1:0] mem_bus;

wire [`OP+`ADDR-1:0] mdr_bus;
wire [`OP+`ADDR-1:0] mem_bus;

reg [`OP+`ADDR-1:0] mdr_reg;
assign mdr_bus = mdr_valid ? mdr_reg : 16'bz;

always @(posedge clk) begin
    if(nrst==0) begin
        mdr_reg <= 0;
    end
    else begin
        if(mdr_load==1) begin
            mdr_reg <= mem_bus;
        end
    end
end

endmodule

verilog_processor/mdr_tb.v
`define OP 8
`define ADDR 8
`timescale 1ns/100ps

module mdr_tb();
// declare the counter signals
reg clk;
reg nrst;
reg mdr_valid;
reg mdr_load;

wire [`OP+`ADDR-1:0] data;
reg [`OP+`ADDR-1:0] memory;

// set up the inital variables and reset
initial begin
    $dumpfile("mdr_tb.vcd");
    $dumpvars();
    $display ("time\t clk reset inc load valid data");
    $monitor ("%g\t %b %b %b %b %b",
    $time, clk, nrst, mdr_load, mdr_valid, data);
    clk = 1;    // initialize the clock to 1
    nrst = 1;   // set the reset to 1 (not reset)
    mdr_valid = 0;
    mdr_load = 0;
    memory = 16'b0000000000001111;
    #5 nrst = 0;    // reset = 0 : resets the counter
    #10 nrst = 1;   // reset back to 1 : counter can start
    #10 mdr_load = 1;
    #10 mdr_load = 0;
    #10 memory = 16'b0000000000001111;
    mdr_valid = 1;
    #50 mdr_valid = 0;  // reset back to 1 : counter can start
    #200 $finish;   // Finish the simulation
end

// Clock generator
always begin
    #5 clk = ~clk;  //clock every 5 time slots
end

// assign data = datareg;

// Connect DUT to test bench
mdr DUT (clk, nrst, mdr_load, mdr_valid, memory, data);

endmodule

verilog_processor/mdr_tb.vcd
$date
	Wed Oct  6 20:38:06 2021
$end
$version
	Icarus Verilog
$end
$timescale
	100ps
$end
$scope module mdr_tb $end
$var wire 16 ! data [15:0] $end
$var reg 1 " clk $end
$var reg 1 # mdr_load $end
$var reg 1 $ mdr_valid $end
$var reg 16 % memory [15:0] $end
$var reg 1 & nrst $end
$scope module DUT $end
$var wire 1 " clk $end
$var wire 1 # mdr_load $end
$var wire 1 $ mdr_valid $end
$var wire 16 ' mem_bus [15:0] $end
$var wire 1 & nrst $end
$var wire 16 ( mdr_bus [15:0] $end
$var reg 16 ) mdr_reg [15:0] $end
$upscope $end
$upscope $end
$enddefinitions $end
#0
$dumpvars
bx )
bz (
b1111 '
1&
b1111 %
0$
0#
1"
bz !
$end
#50
0"
0&
#100
b0 )
1"
#150
0"
1&
#200
1"
#250
0"
1#
#300
b1111 )
1"
#350
0"
0#
#400
1"
#450
b1111 !
b1111 (
0"
1$
#500
1"
#550
0"
#600
1"
#650
0"
#700
1"
#750
0"
#800
1"
#850
0"
#900
1"
#950
bz !
bz (
0"
0$
